Metadata-Version: 2.1
Name: pysiospace
Version: 0.1.7
Summary: PhysioSpace methods for python
Home-page: https://git.rwth-aachen.de/pstumpf/pysiospace
Author: Patrick Stumpf
Author-email: stumpf@combine.rwth-aachen.de
License: MIT license
Keywords: pysiospace
Platform: UNKNOWN
Classifier: Development Status :: 2 - Pre-Alpha
Classifier: Intended Audience :: Developers
Classifier: License :: OSI Approved :: MIT License
Classifier: Natural Language :: English
Classifier: Programming Language :: Python :: 3
Classifier: Programming Language :: Python :: 3.6
Classifier: Programming Language :: Python :: 3.7
Classifier: Programming Language :: Python :: 3.8
Classifier: Programming Language :: Python :: 3.9
Requires-Python: >=3.6
License-File: LICENSE
License-File: AUTHORS.rst
